setup.cfg
setup.py
./rapidconnect/__init__.py
./rapidconnect/listen.py
./rapidconnect/request.py
./rapidconnect/settings.py
RapidConnect.egg-info/PKG-INFO
RapidConnect.egg-info/SOURCES.txt
RapidConnect.egg-info/dependency_links.txt
RapidConnect.egg-info/requires.txt
RapidConnect.egg-info/top_level.txt