Metadata-Version: 1.1
Name: RapidConnect
Version: 0.0.6
Summary: Official Python client for RapidAPI Connect
Home-page: https://github.com/RapidSoftwareSolutions/RapidAPIConnect_Python
Author: Andrey Bukati
Author-email: andrey@rapidapi.com
License: UNKNOWN
Keywords: rapidapi,api,python
Platform: UNKNOWN
Classifier: Development Status :: 4 - Beta
Classifier: Programming Language :: Python :: 2
Classifier: Programming Language :: Python :: 3
